datastar_py/__init__.py
datastar_py/attributes.py
datastar_py/consts.py
datastar_py/django.py
datastar_py/fastapi.py
datastar_py/fasthtml.py
datastar_py/litestar.py
datastar_py/py.typed
datastar_py/quart.py
datastar_py/sanic.py
datastar_py/sse.py
datastar_py/starlette.py
datastar_py-0.8.0.dist-info/METADATA
datastar_py-0.8.0.dist-info/WHEEL
datastar_py-0.8.0.dist-info/licenses/LICENSE.md
datastar_py-0.8.0.dist-info/RECORD
