Metadata-Version: 2.4
Name: datastar-py
Version: 0.8.0
Summary: Helper functions and classes for the Datastar library (https://data-star.dev/)
Project-URL: Documentation, https://github.com/starfederation/datastar-python/blob/develop/README.md
Project-URL: GitHub, https://github.com/starfederation/datastar-python
Author-email: Felix Ingram <f.ingram@gmail.com>, Lucian Knock <git@lucianknock.com>, Chase Sterling <chase.sterling@gmail.com>
License-Expression: MIT
License-File: LICENSE.md
Keywords: datastar,django,fastapi,fasthtml,flask,html,litestar,quart,sanic,starlette
Classifier: Development Status :: 4 - Beta
Classifier: Environment :: Web Environment
Classifier: Intended Audience :: Developers
Classifier: Operating System :: OS Independent
Classifier: Programming Language :: Python
Classifier: Programming Language :: Python :: 3 :: Only
Classifier: Programming Language :: Python :: 3.10
Classifier: Programming Language :: Python :: 3.11
Classifier: Programming Language :: Python :: 3.12
Classifier: Programming Language :: Python :: 3.13
Requires-Python: >=3.10
